acb/README.md
acb/__init__.py
acb/cleanup.py
acb/config.py
acb/config_errors.py
acb/console.py
acb/context.py
acb/debug.py
acb/depends.py
acb/discovery_common.py
acb/logger.py
acb/ssl_config.py
acb/validation.py
acb/actions/README.md
acb/actions/__init__.py
acb/actions/compress/README.md
acb/actions/compress/__init__.py
acb/actions/encode/README.md
acb/actions/encode/__init__.py
acb/actions/hash/README.md
acb/actions/hash/__init__.py
acb/actions/sanitize/README.md
acb/actions/sanitize/__init__.py
acb/actions/secure/README.md
acb/actions/secure/__init__.py
acb/actions/secure/security_patterns.py
acb/actions/validate/README.md
acb/actions/validate/__init__.py
acb/adapters/README.md
acb/adapters/__init__.py
acb/adapters/_tool_adapter_base.py
acb/adapters/ai/README.md
acb/adapters/ai/__init__.py
acb/adapters/ai/_base.py
acb/adapters/ai/cloud.py
acb/adapters/ai/edge.py
acb/adapters/ai/hybrid.py
acb/adapters/cache/README.md
acb/adapters/cache/__init__.py
acb/adapters/cache/_base.py
acb/adapters/cache/memory.py
acb/adapters/cache/redis.py
acb/adapters/dns/README.md
acb/adapters/dns/__init__.py
acb/adapters/dns/_base.py
acb/adapters/dns/cloudflare.py
acb/adapters/dns/gcdns.py
acb/adapters/dns/route53.py
acb/adapters/embedding/README.md
acb/adapters/embedding/__init__.py
acb/adapters/embedding/_base.py
acb/adapters/embedding/huggingface.py
acb/adapters/embedding/lfm.py
acb/adapters/embedding/onnx.py
acb/adapters/embedding/openai.py
acb/adapters/embedding/sentence_transformers.py
acb/adapters/ftpd/README.md
acb/adapters/ftpd/__init__.py
acb/adapters/ftpd/_base.py
acb/adapters/ftpd/ftp.py
acb/adapters/ftpd/sftp.py
acb/adapters/graph/README.md
acb/adapters/graph/__init__.py
acb/adapters/graph/_base.py
acb/adapters/graph/arangodb.py
acb/adapters/graph/duckdb_pgq.py
acb/adapters/graph/neo4j.py
acb/adapters/graph/neptune.py
acb/adapters/logger/README.md
acb/adapters/logger/__init__.py
acb/adapters/logger/_base.py
acb/adapters/logger/logly.py
acb/adapters/logger/loguru.py
acb-0.32.1.dist-info/METADATA
acb-0.32.1.dist-info/WHEEL
acb-0.32.1.dist-info/licenses/LICENSE
acb-0.32.1.dist-info/RECORD
