Metadata-Version: 2.4
Name: acb
Version: 0.32.1
Summary: ACB: Asynchronous Component Base
Project-URL: Documentation, https://github.com/lesleslie/acb
Project-URL: Homepage, https://github.com/lesleslie/acb
Project-URL: Repository, https://github.com/lesleslie/acb
Author-email: lesleslie <les@wedgwoodwebworks.com>
License: BSD-3-CLAUSE
License-File: LICENSE
Classifier: Development Status :: 3 - Alpha
Classifier: Framework :: AsyncIO
Classifier: Framework :: Pydantic
Classifier: Framework :: Pydantic :: 2
Classifier: License :: OSI Approved :: BSD License
Classifier: Operating System :: OS Independent
Classifier: Programming Language :: Python
Classifier: Programming Language :: Python :: 3 :: Only
Classifier: Programming Language :: Python :: 3.13
Classifier: Topic :: Software Development :: Libraries :: Python Modules
Classifier: Typing :: Typed
Requires-Python: <3.14,>=3.13
Requires-Dist: aioconsole>=0.8.2
Requires-Dist: anyio>=4.12.0
Requires-Dist: attrs>=25.4.0
Requires-Dist: bevy>=3.1.0b12
Requires-Dist: blake3>=1.0.8
Requires-Dist: brotli>=1.2.0
Requires-Dist: devtools>=0.12.2
Requires-Dist: dill<0.4.dev0,>=0.3.9
Requires-Dist: google-api-python-client>=2.187.0
Requires-Dist: google-crc32c>=1.7.1
Requires-Dist: icecream>=2.1.8
Requires-Dist: inflection>=0.5.1
Requires-Dist: loguru>=0.7.3
Requires-Dist: msgspec[toml,yaml]
Requires-Dist: nest-asyncio>=1.6.0
Requires-Dist: pydantic-settings>=2.12.0
Requires-Dist: pydantic[email]>=2.12.5
Requires-Dist: pyfiglet>=1.0.4
Requires-Dist: pyyaml>=6.0.3
Requires-Dist: sqlalchemy-utils>=0.42.0
Requires-Dist: sqlalchemy>=2.0.45
Requires-Dist: sqlmodel>=0.0.27
Requires-Dist: toml>=0.10.2
Requires-Dist: tomli-w>=1.2.0
Requires-Dist: urllib3>=2.6.1
Requires-Dist: uuid-utils>=0.12.0
Requires-Dist: uvicorn>=0.38.0
